sign_language_tools/__init__.py
sign_language_tools/pose/__init__.py
sign_language_tools/pose/io/__init__.py
sign_language_tools/pose/io/read.py
sign_language_tools/pose/mediapipe/__init__.py
sign_language_tools/pose/mediapipe/edges.py
sign_language_tools/pose/mediapipe/extraction.py
sign_language_tools/pose/mediapipe/facemesh.py
sign_language_tools/pose/mediapipe/utils.py
sign_language_tools/pose/openpose/__init__.py
sign_language_tools/pose/openpose/edges.py
sign_language_tools/pose/openpose/utils.py
sign_language_tools/pose/transform/__init__.py
sign_language_tools/pose/transform/compose.py
sign_language_tools/pose/transform/filter.py
sign_language_tools/pose/transform/flip.py
sign_language_tools/pose/transform/interpolate.py
sign_language_tools/pose/transform/noise.py
sign_language_tools/pose/transform/normalize.py
sign_language_tools/pose/transform/padding.py
sign_language_tools/pose/transform/resample.py
sign_language_tools/pose/transform/rotate.py
sign_language_tools/pose/transform/scale.py
sign_language_tools/pose/transform/smooth.py
sign_language_tools/pose/transform/translation.py
sign_language_tools/pose/transform/functional/__init__.py
sign_language_tools/pose/transform/functional/interpolation.py
sign_language_tools/visualization/__init__.py
sign_language_tools/visualization/plot/__init__.py
sign_language_tools/visualization/plot/landmarks.py
sign_language_tools/visualization/plot/segments.py
sign_language_tools/visualization/video/__init__.py
sign_language_tools/visualization/video/displayable.py
sign_language_tools/visualization/video/images.py
sign_language_tools/visualization/video/poses.py
sign_language_tools/visualization/video/segments.py
sign_language_tools/visualization/video/video.py
sign_language_tools/visualization/video/video_player.py
sign_language_tools/visualization/video/cv/__init__.py
sign_language_tools/visualization/video/cv/annotations.py
sign_language_tools/visualization/video/cv/landmarks.py
sign_language_tools-0.0.1.dist-info/LICENSE
sign_language_tools-0.0.1.dist-info/METADATA
sign_language_tools-0.0.1.dist-info/WHEEL
sign_language_tools-0.0.1.dist-info/entry_points.txt
sign_language_tools-0.0.1.dist-info/top_level.txt
sign_language_tools-0.0.1.dist-info/RECORD
