Metadata-Version: 2.1
Name: sign-language-tools
Version: 0.0.1
Summary: Python library containing various tools for sign language processing
Author-email: Pierre Poitier <pierre.poitier@unamur.be>, Jérôme Fink <jerome.fink@unamur.be>
License: MIT License
Project-URL: Homepage, https://github.com/ppoitier/sign-language-tools
Keywords: sign language,machine learning,data augmentation,visualization
Classifier: License :: OSI Approved :: MIT License
Classifier: Programming Language :: Python
Classifier: Programming Language :: Python :: 3
Requires-Python: >=3.9
License-File: LICENSE
Requires-Dist: matplotlib
Requires-Dist: mediapipe
Requires-Dist: numpy
Requires-Dist: opencv-python
Requires-Dist: pandas
Requires-Dist: scipy
Requires-Dist: tqdm
Provides-Extra: dev
Requires-Dist: black ; extra == 'dev'
Requires-Dist: pip-tools ; extra == 'dev'
Requires-Dist: pytest ; extra == 'dev'
